tensorboard_plugin_wit/__init__.py
tensorboard_plugin_wit/wit_plugin.py
tensorboard_plugin_wit/wit_plugin_loader.py
tensorboard_plugin_wit/_utils/__init__.py
tensorboard_plugin_wit/_utils/common_utils.py
tensorboard_plugin_wit/_utils/inference_utils.py
tensorboard_plugin_wit/_utils/platform_utils.py
tensorboard_plugin_wit/_vendor/__init__.py
tensorboard_plugin_wit/_vendor/tensorflow_serving/__init__.py
tensorboard_plugin_wit/_vendor/tensorflow_serving/apis/__init__.py
tensorboard_plugin_wit/_vendor/tensorflow_serving/apis/classification_pb2.py
tensorboard_plugin_wit/_vendor/tensorflow_serving/apis/get_model_metadata_pb2.py
tensorboard_plugin_wit/_vendor/tensorflow_serving/apis/get_model_status_pb2.py
tensorboard_plugin_wit/_vendor/tensorflow_serving/apis/inference_pb2.py
tensorboard_plugin_wit/_vendor/tensorflow_serving/apis/input_pb2.py
tensorboard_plugin_wit/_vendor/tensorflow_serving/apis/model_management_pb2.py
tensorboard_plugin_wit/_vendor/tensorflow_serving/apis/model_pb2.py
tensorboard_plugin_wit/_vendor/tensorflow_serving/apis/model_service_pb2.py
tensorboard_plugin_wit/_vendor/tensorflow_serving/apis/model_service_pb2_grpc.py
tensorboard_plugin_wit/_vendor/tensorflow_serving/apis/predict_pb2.py
tensorboard_plugin_wit/_vendor/tensorflow_serving/apis/prediction_log_pb2.py
tensorboard_plugin_wit/_vendor/tensorflow_serving/apis/prediction_service_pb2.py
tensorboard_plugin_wit/_vendor/tensorflow_serving/apis/prediction_service_pb2_grpc.py
tensorboard_plugin_wit/_vendor/tensorflow_serving/apis/regression_pb2.py
tensorboard_plugin_wit/_vendor/tensorflow_serving/apis/session_service_pb2.py
tensorboard_plugin_wit/_vendor/tensorflow_serving/config/__init__.py
tensorboard_plugin_wit/_vendor/tensorflow_serving/config/log_collector_config_pb2.py
tensorboard_plugin_wit/_vendor/tensorflow_serving/config/logging_config_pb2.py
tensorboard_plugin_wit/_vendor/tensorflow_serving/config/model_server_config_pb2.py
tensorboard_plugin_wit-1.6.0.post2.dist-info/METADATA
tensorboard_plugin_wit-1.6.0.post2.dist-info/WHEEL
tensorboard_plugin_wit-1.6.0.post2.dist-info/entry_points.txt
tensorboard_plugin_wit-1.6.0.post2.dist-info/top_level.txt
tensorboard_plugin_wit-1.6.0.post2.dist-info/RECORD
