Metadata-Version: 2.1
Name: tensorboard-plugin-wit
Version: 1.6.0.post2
Summary: What-If Tool TensorBoard plugin.
Home-page: UNKNOWN
Author: UNKNOWN
Author-email: UNKNOWN
License: UNKNOWN
Platform: UNKNOWN
